{
  "1": ["Patatas con bacalao", "Arroz seco montañés", "Pinchos", "Croquetas"],
  "2": ["Arroz caldoso de puchero con pelota", "Spaghettis", "Lomo ajitos", "Chipirones"],
  "3": ["Fideuá", "Sopa menudillos", "Pataqueta", "Merluza"],
  "4": ["-", "-", "-", "-"],
  "5": ["-", "-", "-", "-"],
  "6": ["Hervido", "Arroz caldoso conejo y pollo", "Sándwich vegetal", "Tortilla gambas"],
  "7": ["Sopa marisco con fideos", "Arroz a la cubana", "Lomo con tomate", "Boquerón frito"],
  "8": ["Paella marisco", "Sopa de ajo", "Ensalada pasta", "Flauta de jamón y queso"],
  "9": ["-", "-", "-", "-"],
  "10": ["-", "-", "-", "-"],
  "11": ["-", "-", "-", "-"],
  "12": ["-", "-", "-", "-"],
  "13": ["Macarrones", "Arroz a la cubana", "Ensalada ahumados", "Dorada"],
  "14": ["Arroz meloso con gamba", "Potaje", "Tortilla al gusto", "Pollo al horno"],
  "15": ["Lentejas", "Arroz horno", "Pechuga de pollo", "Huevos rotos"],
  "16": ["Gazpachos", "Arroz horno con patatas y tomate", "Hamburguesa", "Bacalao frito"],
  "17": ["Paella con habas y alcachofas", "Sopa de fideos con pollo", "Albóndigas carne", "Chipirones"],
  "18": ["-", "-", "-", "-"],
  "19": ["-", "-", "-", "-"],
  "20": ["Guisado", "Hervido", "Chipirones", "Huevos con bacón"],
  "21": ["Arroz meloso con acelgas", "Fideuá", "Pechuga", "Merluza"],
  "22": ["Alubias", "Paella valenciana", "Boquerón frito", "Pinchos"],
  "23": ["Pimientos rellenos", "Sopa castellana", "Alitas pollo", "Chipirones"],
  "24": ["Ensaladilla sepia", "Arroz horno", "Sándwichs de pollo", "Albóndigas carne"],
  "25": ["-", "-", "-", "-"],
  "26": ["-", "-", "-", "-"],
  "27": ["Spaghettis", "Arroz meloso montañés", "Ensalada ahumados", "Chipirones plancha"],
  "28": ["Arroz horno de patata y tomate", "Sopa marisco con fideos", "Croquetas", "Lomo con tomate"],
  "29": ["Lentejas", "Paella de bacalao y coliflor", "Dorada", "Pollo al horno"],
  "30": ["Gazpachos", "Arroz a la cubana", "Sardinas", "Pechuga pollo"],
  "31": ["Paella valenciana", "Sopa de verduras", "Flauta de jamón y queso", "Merluza"]
}